LICENSE
MANIFEST.in
README.md
setup.py
TriePy.egg-info/PKG-INFO
TriePy.egg-info/SOURCES.txt
TriePy.egg-info/dependency_links.txt
TriePy.egg-info/top_level.txt
trie/__init__.py
trie/trie.py