Metadata-Version: 1.0
Name: TriePy
Version: 0.1.4
Summary: Simple Python Trie Data Structure
Home-page: UNKNOWN
Author: Adrian Cruz
Author-email: drincruz@gmail.com
License: BSD
Platform: UNKNOWN
